glyptic/__init__.py
glyptic/enhance_fingerprints.py
glyptic/enhance_utils.py
glyptic/glyptic_setup.py
glyptic/glyptic_workflow.py
glyptic/unet_weights.hdf5
glyptic/internal/.gitattributes
glyptic/internal/.gitignore
glyptic/internal/.pylintrc
glyptic/internal/CODEOWNERS
glyptic/internal/CONTRIBUTING.md
glyptic/internal/LICENSE
glyptic/internal/README.md
glyptic/internal/comfyui_screenshot.png
glyptic/internal/cuda_malloc.py
glyptic/internal/execution.py
glyptic/internal/extra_model_paths.yaml
glyptic/internal/extra_model_paths.yaml.example
glyptic/internal/fix_torch.py
glyptic/internal/folder_paths.py
glyptic/internal/latent_preview.py
glyptic/internal/main.py
glyptic/internal/new_updater.py
glyptic/internal/node_helpers.py
glyptic/internal/nodes.py
glyptic/internal/pytest.ini
glyptic/internal/requirements.txt
glyptic/internal/server.py
glyptic/internal/.ci/update_windows/update.py
glyptic/internal/.ci/update_windows/update_comfyui.bat
glyptic/internal/.ci/update_windows/update_comfyui_stable.bat
glyptic/internal/.ci/windows_base_files/README_VERY_IMPORTANT.txt
glyptic/internal/.ci/windows_base_files/run_cpu.bat
glyptic/internal/.ci/windows_base_files/run_nvidia_gpu.bat
glyptic/internal/.ci/windows_nightly_base_files/run_nvidia_gpu_fast.bat
glyptic/internal/.github/ISSUE_TEMPLATE/bug-report.yml
glyptic/internal/.github/ISSUE_TEMPLATE/config.yml
glyptic/internal/.github/ISSUE_TEMPLATE/feature-request.yml
glyptic/internal/.github/ISSUE_TEMPLATE/user-support.yml
glyptic/internal/.github/workflows/pullrequest-ci-run.yml
glyptic/internal/.github/workflows/pylint.yml
glyptic/internal/.github/workflows/stable-release.yml
glyptic/internal/.github/workflows/stale-issues.yml
glyptic/internal/.github/workflows/test-build.yml
glyptic/internal/.github/workflows/test-ci.yml
glyptic/internal/.github/workflows/test-launch.yml
glyptic/internal/.github/workflows/test-unit.yml
glyptic/internal/.github/workflows/windows_release_dependencies.yml
glyptic-0.1.2.dist-info/METADATA
glyptic-0.1.2.dist-info/WHEEL
glyptic-0.1.2.dist-info/entry_points.txt
glyptic-0.1.2.dist-info/licenses/COPYING
glyptic-0.1.2.dist-info/RECORD
