Metadata-Version: 2.3
Name: glyptic
Version: 0.1.2
Summary: Dactylogram to intaglio for your carcanets.
Project-URL: Repository, https://github.com/tariks/glyptic.git
Author-email: Tarik Salameh <tarik.salameh@gmail.com>
License-File: COPYING
Keywords: fingerprint,fingerprint enhancement,image-to-image,img2img,jewelry engraving,sdxl,stable diffusion
Classifier: Development Status :: 4 - Beta
Classifier: Environment :: GPU
Classifier: Intended Audience :: Other Audience
Classifier: License :: OSI Approved :: GNU General Public License v3 (GPLv3)
Classifier: Programming Language :: Python :: 3.12
Classifier: Topic :: Artistic Software
Classifier: Topic :: Multimedia :: Graphics
Classifier: Topic :: Scientific/Engineering :: Image Processing
Requires-Python: >=3.12
Requires-Dist: aiohttp>=3.10.5
Requires-Dist: comfy-script[default]>=0.5.1
Requires-Dist: einops>=0.8.0
Requires-Dist: huggingface-hub>=0.25.0
Requires-Dist: keras-preprocessing>=1.1.2
Requires-Dist: keras>=3.5.0
Requires-Dist: opencv-python>=4.10.0.84
Requires-Dist: pillow>=10.4.0
Requires-Dist: pip>=24.2
Requires-Dist: psutil>=6.0.0
Requires-Dist: pyyaml>=6.0.2
Requires-Dist: safetensors>=0.4.2
Requires-Dist: scikit-image>=0.24.0
Requires-Dist: scipy>=1.14.1
Requires-Dist: sentencepiece>=0.2.0
Requires-Dist: tensorflow>=2.17.0
Requires-Dist: tokenizers>=0.13.3
Requires-Dist: torch>=2.4.1
Requires-Dist: torchaudio>=2.4.1
Requires-Dist: torchsde>=0.2.6
Requires-Dist: torchvision>=0.19.1
Requires-Dist: tqdm>=4.66.5
Requires-Dist: transformers>=4.28.1
Requires-Dist: vtracer>=0.6.11
Requires-Dist: xdg-base-dirs>=6.0.1
